BWStatsWrapper/Exp2LevelCalculator.py
BWStatsWrapper/__init__.py
BWStatsWrapper/main.py
BWStatsWrapper/object.py
BWStatsWrapper-0.2.dist-info/METADATA
BWStatsWrapper-0.2.dist-info/WHEEL
BWStatsWrapper-0.2.dist-info/top_level.txt
BWStatsWrapper-0.2.dist-info/RECORD
