Metadata-Version: 2.1
Name: BWStatsWrapper
Version: 0.2
Summary: Easily access Bedwars stats of a Hypixel player.
Home-page: https://github.com/Heknon/Bedwars-Stats-Wrapper-Python
Author: Ori Harel
Author-email: heknonplayz@gmail.com
License: UNKNOWN
Platform: UNKNOWN
Classifier: Programming Language :: Python :: 3
Classifier: License :: OSI Approved :: MIT License
Classifier: Operating System :: OS Independent
Requires-Dist: requests
Requires-Dist: pathlib
